{
  "id": "001",
  "description": "Policy example 1",
  "metadata": "",
  "object_conditions": [{
    "attribute": "Presence.timeStamp",
    "value": "5 pm",
    "operator": ">="
  },
    {
      "attribute": "Presence.timeStamp",
      "value": "7 pm",
      "operator": "<="
    },
    {
      "attribute": "Presence.timeStamp",
      "value": "Alice",
      "operator": "="
    }
  ],
  "querier_conditions": [{
    "attribute": "Query.timeStamp",
    "value": "6 pm",
    "operator": ">="
  },
    {
      "attribute": "Query.timeStamp",
      "value": "8 pm",
      "operator": "<="
    },
    {
      "attribute": "Query.user_name",
      "value": "John",
      "operator": "="
    }
  ],
  "purpose": "",
  "action": ""
}